cyrex/__init__.py
cyrex/analyzer.py
cyrex/reporter.py
cyrex/scanner.py
cyrex/utils.py
cyrex-0.1.0.dist-info/METADATA
cyrex-0.1.0.dist-info/WHEEL
cyrex-0.1.0.dist-info/top_level.txt
cyrex-0.1.0.dist-info/RECORD
