Metadata-Version: 2.4
Name: cyrex
Version: 0.1.0
Summary: A static code analyzer for Python to detect unused code, long functions, and TODOs.
Author-email: Zain ul Abideen <zainthenpc05@gmail.com>
Project-URL: Homepage, https://github.com/zain-the-npc/Cyrex.git
Classifier: Programming Language :: Python :: 3
Classifier: License :: OSI Approved :: MIT License
Classifier: Operating System :: OS Independent
Requires-Python: >=3.7
